pyscribble/__init__.py
pyscribble-0.1.2.dist-info/METADATA
pyscribble-0.1.2.dist-info/WHEEL
pyscribble-0.1.2.dist-info/top_level.txt
pyscribble-0.1.2.dist-info/RECORD
